metahyper/__init__.py
metahyper/_locker.py
metahyper/api.py
metahyper/status.py
metahyper/utils.py
metahyper_examples/minimal/run.py
metahyper-0.5.6.dist-info/LICENSE
metahyper-0.5.6.dist-info/WHEEL
metahyper-0.5.6.dist-info/METADATA
metahyper-0.5.6.dist-info/RECORD
