Metadata-Version: 2.1
Name: metahyper
Version: 0.5.6
Summary: Parallelisation and distribution framework for neural pipeline search algorithms.
Home-page: https://github.com/automl/metahyper
License: MIT
Keywords: Paralellisation,AutoML,Hyperparameter Optimization,Neural Architecture Search,Neural Pipeline Search
Author: Danny Stoll
Author-email: stolld@cs.uni-freiburg.de
Requires-Python: >=3.7.1,<3.11
Classifier: Development Status :: 4 - Beta
Classifier: Intended Audience :: Developers
Classifier: Intended Audience :: Science/Research
Classifier: License :: OSI Approved :: MIT License
Classifier: Natural Language :: English
Classifier: Operating System :: Unix
Classifier: Programming Language :: Python :: 3
Classifier: Programming Language :: Python :: 3.10
Classifier: Programming Language :: Python :: 3.7
Classifier: Programming Language :: Python :: 3.8
Classifier: Programming Language :: Python :: 3.9
Classifier: Topic :: Scientific/Engineering :: Artificial Intelligence
Classifier: Topic :: System :: Distributed Computing
Requires-Dist: PyYAML (>=6.0,<7.0)
Requires-Dist: dill (>=0.3.4,<0.4.0)
Requires-Dist: mkdocs (>=1.3.0,<2.0.0)
Requires-Dist: more-itertools (>=8.12.0,<9.0.0)
Requires-Dist: numpy (>=1.21.1,<2.0.0)
Requires-Dist: types-PyYAML (>=6.0.4,<7.0.0)
Project-URL: Repository, https://github.com/automl/metahyper
